terraform_chart/__init__.py
terraform_chart/terraform.sh
terraform_chart/terraform_cli.py
terraform_chart-0.1.dist-info/METADATA
terraform_chart-0.1.dist-info/WHEEL
terraform_chart-0.1.dist-info/entry_points.txt
terraform_chart-0.1.dist-info/top_level.txt
terraform_chart-0.1.dist-info/RECORD
