Metadata-Version: 2.1
Name: terraform-chart
Version: 0.1
Requires-Dist: Click
